datawatts/__init__.py
datawatts/datassette.py
datawatts/menu.py
datawatts/run.py
datawatts/watts.py
datawatts-0.1.4.dist-info/DESCRIPTION.rst
datawatts-0.1.4.dist-info/METADATA
datawatts-0.1.4.dist-info/RECORD
datawatts-0.1.4.dist-info/WHEEL
datawatts-0.1.4.dist-info/entry_points.txt
datawatts-0.1.4.dist-info/metadata.json
datawatts-0.1.4.dist-info/top_level.txt
